betterepd7in5.py
betterepd7in5-0.2.1.dist-info/METADATA
betterepd7in5-0.2.1.dist-info/WHEEL
betterepd7in5-0.2.1.dist-info/licenses/LICENSE.txt
betterepd7in5-0.2.1.dist-info/RECORD
