Metadata-Version: 2.4
Name: betterepd7in5
Version: 0.2.1
Summary: Better Raspberry Pi Python driver for Waveshare's 7.5" V2 e-paper display
Author-email: Hugo Chargois <hugo.chargois@free.fr>
License-File: LICENSE.txt
Requires-Python: >=3.12
Requires-Dist: gpiozero>=2.0.1
Requires-Dist: lgpio>=0.2.2.0
Requires-Dist: numpy>=2.2.3
Requires-Dist: pillow>=11.1.0
Requires-Dist: spidev>=3.6
